{
  "parent": "minecraft:item/handheld",
  "loader": "forge:separate_transforms",
  "base": {
    "textures": {
      "book": "spector_spellbooks:item/spector_spell_book",
      "particle": "spector_spellbooks:item/spector_spell_book"
    },
    "parent": "irons_spellbooks:item/template_spell_book_model"
  },
  "perspectives": {
    "gui": {
      "parent": "item/generated",
      "textures": {
        "layer0": "spector_spellbooks:item/spector_spell_book_gui"
      }
    },
    "head": {
      "textures": {
        "book": "spector_spellbooks:item/spector_spell_book",
        "particle": "spector_spellbooks:item/spector_spell_book"
      },
      "parent": "irons_spellbooks:item/template_spell_book_model_open"
    }
  }
}